LICENSE
MANIFEST.in
README.md
setup.py
pynanoleaf/__init__.py
pynanoleaf/pynanoleaf.py
pynanoleaf.egg-info/PKG-INFO
pynanoleaf.egg-info/SOURCES.txt
pynanoleaf.egg-info/dependency_links.txt
pynanoleaf.egg-info/requires.txt
pynanoleaf.egg-info/top_level.txt