Metadata-Version: 2.1
Name: pynanoleaf
Version: 0.1.1
Summary: A Python3 wrapper for the Nanoleaf API
Home-page: https://github.com/Oro/pynanoleaf
Author: Marco Orovecchia
Author-email: pynanoleaf@marco.orovecchia.com
License: UNKNOWN
Platform: UNKNOWN
Classifier: License :: OSI Approved :: MIT License
Classifier: Programming Language :: Python :: 3
Classifier: Topic :: Home Automation
Classifier: Operating System :: OS Independent
